g2pM/__init__.py
g2pM/char2idx.pkl
g2pM/class2idx.pkl
g2pM/digest_cedict.pkl
g2pM/g2pM.py
g2pM/np_ckpt.pkl
g2pM-0.1.2.5.dist-info/LICENSE
g2pM-0.1.2.5.dist-info/METADATA
g2pM-0.1.2.5.dist-info/WHEEL
g2pM-0.1.2.5.dist-info/top_level.txt
g2pM-0.1.2.5.dist-info/RECORD
