Metadata-Version: 2.1
Name: g2pM
Version: 0.1.2.5
Summary: g2pM: A Neural Grapheme-to-Phoneme Conversion Package for MandarinChinese
Home-page: https://github.com/kakaobrain/g2pM
Author: Seanie Lee
Author-email: lsnfamily02@gmail.com
License: Apache License 2.0
Platform: UNKNOWN
Classifier: Development Status :: 5 - Production/Stable
Classifier: Intended Audience :: Developers
Classifier: Intended Audience :: Science/Research
Classifier: License :: OSI Approved :: Apache Software License
Classifier: Operating System :: OS Independent
Classifier: Programming Language :: Python :: 3
Classifier: Programming Language :: Python :: 3.6
Classifier: Programming Language :: Python :: 3.7
Requires-Python: >=3.6
